[{"identifier":"5661027","themes":["schema:Event","schema:SaleEvent","BricABrac","EntertainmentAndEvent","Market","PointOfInterest","SaleEvent"],"itemNameFr":"Docks du livre","startDate":"2024-01-06","endDate":"2024-12-21","startTime":"09:00:00","endTime":"18:00:00","address":["Cours D'Estienne d'Orves","Cours d'Estienne d'Orves"],"city":"Marseille 1er Arrondissement","zip":"13001","lat":"43.292519","lng":"5.373065","schemaLogo":null,"tel":null,"web":null,"img":null,"descriptionFr":"Livres reliés, illustrés, éditions originales, livres documentaires : Provence, littérature, sciences et techniques , histoire, géographie, sciences humaines, arts. BD, affiches de cinéma et vinyles?","shortDescriptionFr":"L'Association pour la Promotion Active du Livre à Marseille propose un marché du livre réunissant une dizaine de libraires professionnels, avec des livres anciens et modernes sur tous les sujets.","price":null,"minPrice":null,"maxPrice":null},{"identifier":"FMAAQU064V5BSD0K","themes":["schema:Event","schema:SaleEvent","BricABrac","EntertainmentAndEvent","PointOfInterest","SaleEvent"],"itemNameFr":"Marché à la brocante","creationDate":"2023-12-22","startDate":"2024-10-02","endDate":"2024-10-02","startTime":null,"endTime":null,"address":["Parc Saint Joseph"],"city":"Cambo-les-Bains","zip":"64250","lat":"43.3605565","lng":"-1.3999053","schemaLogo":"http://aquitaine.media.tourinsoft.eu/upload/Logo-Sirtaqui-1280x405.jpg","tel":["+33 5 59 93 74 30"],"web":null,"img":"http://aquitaine.media.tourinsoft.eu/Upload/Photos-1440x900-Tourinsoft--8--2.jpg","descriptionFr":null,"shortDescriptionFr":null,"price":null,"minPrice":null,"maxPrice":null}]